bst/__init__.py
bst/core.py
pythonic_bst-1.0.3.dist-info/LICENSE.md
pythonic_bst-1.0.3.dist-info/METADATA
pythonic_bst-1.0.3.dist-info/WHEEL
pythonic_bst-1.0.3.dist-info/top_level.txt
pythonic_bst-1.0.3.dist-info/RECORD
