Metadata-Version: 2.1
Name: pythonic-bst
Version: 1.0.3
Summary: Minimalistic, unbalanced Binary Search Tree
Author-email: Giovanni Squillero <giovanni.squillero@polito.it>
License: 0BSD
Project-URL: Homepage, https://github.com/squillero/pythonic-bst
Keywords: Binary Search Tree,Data Structures,BST
Classifier: Development Status :: 5 - Production/Stable
Classifier: Intended Audience :: Information Technology
Classifier: Intended Audience :: Science/Research
Classifier: License :: OSI Approved :: BSD License
Classifier: Programming Language :: Python :: 3
Classifier: Programming Language :: Python
Classifier: Topic :: Software Development :: Libraries
Requires-Python: >=3.7
License-File: LICENSE.md
Provides-Extra: dev
Requires-Dist: pytest ; extra == 'dev'
Requires-Dist: Coverage.py ; extra == 'dev'
Requires-Dist: bumpver ; extra == 'dev'
